CssQuanweiZhinan4th/README.md
CssQuanweiZhinan4th/__init__.py
CssQuanweiZhinan4th/__main__.py
CssQuanweiZhinan4th/file.epub
CssQuanweiZhinan4th/index.html
CssQuanweiZhinan4th/css/__init__.py
CssQuanweiZhinan4th/css/annotations.css
CssQuanweiZhinan4th/css/main.css
CssQuanweiZhinan4th/css/normalize.css
CssQuanweiZhinan4th/css/popup.css
CssQuanweiZhinan4th/font/__init__.py
CssQuanweiZhinan4th/font/fontello.eot
CssQuanweiZhinan4th/font/fontello.svg
CssQuanweiZhinan4th/font/fontello.ttf
CssQuanweiZhinan4th/font/fontello.woff
CssQuanweiZhinan4th/img/__init__.py
CssQuanweiZhinan4th/img/annotator-glyph-sprite.png
CssQuanweiZhinan4th/img/annotator-icon-sprite.png
CssQuanweiZhinan4th/img/apple-touch-icon.png
CssQuanweiZhinan4th/img/cancelfullscreen.png
CssQuanweiZhinan4th/img/close.png
CssQuanweiZhinan4th/img/fullscreen.png
CssQuanweiZhinan4th/img/loader.gif
CssQuanweiZhinan4th/img/menu-icon.png
CssQuanweiZhinan4th/img/save.png
CssQuanweiZhinan4th/img/saved.png
CssQuanweiZhinan4th/img/settings-s.png
CssQuanweiZhinan4th/img/settings.png
CssQuanweiZhinan4th/img/star.png
CssQuanweiZhinan4th/js/__init__.py
CssQuanweiZhinan4th/js/epub.js
CssQuanweiZhinan4th/js/epub.min.js
CssQuanweiZhinan4th/js/epub.min.map
CssQuanweiZhinan4th/js/hooks.min.js
CssQuanweiZhinan4th/js/hooks.min.map
CssQuanweiZhinan4th/js/reader.js
CssQuanweiZhinan4th/js/reader.js.map
CssQuanweiZhinan4th/js/reader.min.js
CssQuanweiZhinan4th/js/reader.min.map
CssQuanweiZhinan4th/js/hooks/__init__.py
CssQuanweiZhinan4th/js/hooks/extensions/__init__.py
CssQuanweiZhinan4th/js/hooks/extensions/highlight.js
CssQuanweiZhinan4th/js/libs/__init__.py
CssQuanweiZhinan4th/js/libs/jquery.min.js
CssQuanweiZhinan4th/js/libs/localforage.min.js
CssQuanweiZhinan4th/js/libs/screenfull.js
CssQuanweiZhinan4th/js/libs/screenfull.min.js
CssQuanweiZhinan4th/js/libs/zip.min.js
CssQuanweiZhinan4th/js/plugins/__init__.py
CssQuanweiZhinan4th/js/plugins/hypothesis.js
CssQuanweiZhinan4th/js/plugins/search.js
css_quanwei_zhinan_4th-2024.3.5.0.dist-info/METADATA
css_quanwei_zhinan_4th-2024.3.5.0.dist-info/WHEEL
css_quanwei_zhinan_4th-2024.3.5.0.dist-info/entry_points.txt
css_quanwei_zhinan_4th-2024.3.5.0.dist-info/top_level.txt
css_quanwei_zhinan_4th-2024.3.5.0.dist-info/RECORD
